trustformers-0.1.0a1.dist-info/METADATA
trustformers-0.1.0a1.dist-info/WHEEL
trustformers-0.1.0a1.dist-info/licenses/LICENSE
trustformers.libs/libgfortran-3ec47101.so.5
trustformers.libs/libopenblas-1dedc9fe.so.0
trustformers.libs/libquadmath-67d31475.so.0
trustformers/__init__.py
trustformers/__init___original.py
trustformers/_trustformers.abi3.so
trustformers/_trustformers.pyi
trustformers/advanced_numpy.py
trustformers/async_utils.py
trustformers/auto_config.py
trustformers/batch_encoding.py
trustformers/caching.py
trustformers/config_manager.py
trustformers/configuration_bert.py
trustformers/configuration_gpt2.py
trustformers/configuration_llama.py
trustformers/configuration_t5.py
trustformers/data_collator.py
trustformers/data_science_tools.py
trustformers/debugging.py
trustformers/distributed_training.py
trustformers/evaluation.py
trustformers/extensions.py
trustformers/generation_utils.py
trustformers/jax_integration.py
trustformers/jax_utils.py
trustformers/jupyter_support.py
trustformers/mlops_integration.py
trustformers/modeling_bert.py
trustformers/modeling_gpt2.py
trustformers/modeling_llama.py
trustformers/modeling_t5.py
trustformers/modeling_utils.py
trustformers/numpy_utils.py
trustformers/performance.py
trustformers/pipelines.py
trustformers/py.typed
trustformers/pytorch_advanced.py
trustformers/serving.py
trustformers/tokenization_utils.py
trustformers/tokenizer_advanced.py
trustformers/torch_module_compat.py
trustformers/torch_utils.py
trustformers/trainer_utils.py
trustformers/type_validation.py
trustformers/utils.py
trustformers-0.1.0a1.dist-info/RECORD
