Metadata-Version: 2.4
Name: trustformers
Version: 0.1.0a1
Classifier: Programming Language :: Rust
Classifier: Programming Language :: Python :: Implementation :: CPython
Classifier: Programming Language :: Python :: 3
Classifier: Programming Language :: Python :: 3.8
Classifier: Programming Language :: Python :: 3.9
Classifier: Programming Language :: Python :: 3.10
Classifier: Programming Language :: Python :: 3.11
Classifier: Programming Language :: Python :: 3.12
Classifier: License :: OSI Approved :: Apache Software License
Classifier: Development Status :: 4 - Beta
Classifier: Intended Audience :: Developers
Classifier: Intended Audience :: Science/Research
Classifier: Topic :: Scientific/Engineering :: Artificial Intelligence
Classifier: Topic :: Software Development :: Libraries :: Python Modules
Requires-Dist: numpy>=1.21.0
Requires-Dist: tqdm>=4.62.0
Requires-Dist: requests>=2.26.0
Requires-Dist: regex>=2021.8.3
Requires-Dist: pyyaml>=5.4.1
Requires-Dist: packaging>=20.0
Requires-Dist: torch>=1.9.0 ; extra == 'torch'
Requires-Dist: tensorflow>=2.5.0 ; extra == 'tensorflow'
Requires-Dist: pytest>=6.0 ; extra == 'dev'
Requires-Dist: pytest-cov>=2.0 ; extra == 'dev'
Requires-Dist: black>=22.0 ; extra == 'dev'
Requires-Dist: isort>=5.0 ; extra == 'dev'
Requires-Dist: mypy>=0.910 ; extra == 'dev'
Requires-Dist: ruff>=0.0.261 ; extra == 'dev'
Requires-Dist: torch>=1.9.0 ; extra == 'all'
Requires-Dist: tensorflow>=2.5.0 ; extra == 'all'
Provides-Extra: torch
Provides-Extra: tensorflow
Provides-Extra: dev
Provides-Extra: all
License-File: LICENSE
Summary: High-performance transformer library for Python, written in Rust
Keywords: transformers,machine-learning,nlp,deep-learning,pytorch,huggingface
Author-email: TrustformeRS Team <contact@trustformers.dev>
License: Apache-2.0
Requires-Python: >=3.8
Project-URL: Homepage, https://github.com/cool-japan/trustformers
Project-URL: Documentation, https://trustformers.readthedocs.io
Project-URL: Repository, https://github.com/cool-japan/trustformers
Project-URL: Issues, https://github.com/cool-japan/trustformers/issues
